CHANGELOG.txt
LICENSE.txt
MANIFEST.in
README.rst
setup.cfg
setup.py
PyENCODE.egg-info/PKG-INFO
PyENCODE.egg-info/SOURCES.txt
PyENCODE.egg-info/dependency_links.txt
PyENCODE.egg-info/requires.txt
PyENCODE.egg-info/top_level.txt
PyENCODE.egg-info/zip-safe
pyencode/__init__.py
pyencode/_gzip.py
pyencode/cache.py
pyencode/encode.py
pyencode/util.py