Metadata-Version: 1.1
Name: PyENCODE
Version: 0.2
Summary: Convenience package for accessing ENCODE (Encyclopedia of DNA Elements) project data at UCSC
Home-page: http://kt.era.ee/
Author: Konstantin Tretyakov
Author-email: kt@ut.ee
License: MIT
Keywords: bioinformatics data-access encode
Platform: UNKNOWN
Classifier: Development Status :: 3 - Alpha
Classifier: Programming Language :: Python
Classifier: Intended Audience :: Science/Research
Classifier: License :: OSI Approved :: MIT License
Classifier: Topic :: Scientific/Engineering :: Bio-Informatics
